eurelis_langchain_solr_vectorstore/__init__.py
eurelis_langchain_solr_vectorstore/solr_core.py
eurelis_langchain_solr_vectorstore/types.py
eurelis_langchain_solr_vectorstore-0.0.3.dist-info/LICENSE
eurelis_langchain_solr_vectorstore-0.0.3.dist-info/METADATA
eurelis_langchain_solr_vectorstore-0.0.3.dist-info/WHEEL
eurelis_langchain_solr_vectorstore-0.0.3.dist-info/top_level.txt
eurelis_langchain_solr_vectorstore-0.0.3.dist-info/RECORD
