Metadata-Version: 2.1
Name: eurelis_langchain_solr_vectorstore
Version: 0.0.3
Summary: Library that provide a Solr based vector store for Langchain
Author-email: Jérôme DIAZ <j.diaz@eurelis.com>, Vincent LAMBERT <v.lambert@eurelis.com>
Project-URL: Homepage, https://github.com/Eurelis/Eurelis-Langchain-SolR-VectorStore
Project-URL: Bug Tracker, https://github.com/Eurelis/Eurelis-Langchain-SolR-VectorStore/issues
Classifier: Programming Language :: Python :: 3
Classifier: License :: OSI Approved :: MIT License
Classifier: Operating System :: OS Independent
Requires-Python: >=3.11
License-File: LICENSE
